[
    {
        "Title":"Développeur Front-End",
        "ShortDescription":"Chez BattleKart, j'ai activement participé à la conception et au développement d'une multitude de modules internes essentiels pour optimiser la gestion des opérations. J'ai notamment créé des pages de centres dynamiques et administrables via ces modules, permettant une personnalisation flexible du contenu. Mon travail a également inclus une contribution significative au développement du nouveau site internet de l'entreprise.",
        "LongDescription":"",
        "DateDebutContrat":"Octobre 2022",
        "DateFinContrat":"",
        "Technos": [
            "Angular",
            "TypeScript",
            "TailwindCSS",
            "Git"
        ]
    }
]